{"rejected":{"HISTOGRAM":{"com.oltpbenchmark.benchmarks.hot.procedures.ReadModifyWrite/01":5797},"NUM_SAMPLES":5797,"VALUE_TYPE":"com.oltpbenchmark.api.TransactionType"},"aborted":{"HISTOGRAM":{},"NUM_SAMPLES":0},"unexpected":{"HISTOGRAM":{"com.oltpbenchmark.benchmarks.hot.procedures.ReadModifyWrite/01":572},"NUM_SAMPLES":572,"VALUE_TYPE":"com.oltpbenchmark.api.TransactionType"},"completed":{"HISTOGRAM":{"com.oltpbenchmark.benchmarks.hot.procedures.ReadModifyWrite/01":1181,"com.oltpbenchmark.benchmarks.hot.procedures.RMWLocalRORemote/02":0},"NUM_SAMPLES":1181,"KEEP_ZERO_ENTRIES":true,"VALUE_TYPE":"com.oltpbenchmark.api.TransactionType"}}